{"name":"docker-library-php","repo":"library/php","tags":[{"name":"8.4.8","full_size":187129000,"v2":true,"tag_last_pushed":"2025-06-11T02:10:45.423126Z"},{"name":"8.3.22","full_size":181355496,"v2":true,"tag_last_pushed":"2025-06-11T02:09:07.098733Z"},{"name":"8.2.28","full_size":180494370,"v2":true,"tag_last_pushed":"2025-06-11T02:04:33.829497Z"},{"name":"8.1.32","full_size":179758999,"v2":true,"tag_last_pushed":"2025-06-11T02:00:43.584359Z"},{"name":"8.4.7","full_size":187122067,"v2":true,"tag_last_pushed":"2025-05-22T05:02:54.536496Z"},{"name":"8.3.21","full_size":181361333,"v2":true,"tag_last_pushed":"2025-05-22T05:01:28.925815Z"},{"name":"8.3.20","full_size":181345323,"v2":true,"tag_last_pushed":"2025-04-29T04:58:47.119476Z"},{"name":"8.4.6","full_size":187117212,"v2":true,"tag_last_pushed":"2025-04-29T02:10:51.404037Z"}],"suffix":["-zts-alpine","-zts","-fpm-alpine","-fpm","-cli-alpine","-cli","-apache","-alpine"],"fixed_tags":["zts","zts-alpine"],"latest_tags":["8.4.8"],"created_time":"2025-06-11 04:01:47"}