{"name":"docker-elastic-kibana","repo":"elastic/kibana","tags":[{"name":"8.15.2","full_size":412688028,"v2":true,"tag_last_pushed":"2024-09-26T08:12:22.034206Z"},{"name":"7.17.24","full_size":363545034,"v2":true,"tag_last_pushed":"2024-09-10T08:23:50.057729Z"},{"name":"8.15.1","full_size":412297212,"v2":true,"tag_last_pushed":"2024-09-05T16:40:07.580289Z"},{"name":"8.15.0","full_size":420099980,"v2":true,"tag_last_pushed":"2024-08-08T13:09:35.739999Z"},{"name":"7.17.23","full_size":362524744,"v2":true,"tag_last_pushed":"2024-07-30T15:42:38.25415Z"},{"name":"8.14.3","full_size":413760390,"v2":true,"tag_last_pushed":"2024-07-11T08:09:48.854121Z"},{"name":"8.14.2","full_size":413563540,"v2":true,"tag_last_pushed":"2024-07-04T08:03:04.612661Z"},{"name":"7.17.22","full_size":376274702,"v2":true,"tag_last_pushed":"2024-06-13T13:29:04.976477Z"},{"name":"8.14.1","full_size":413432074,"v2":true,"tag_last_pushed":"2024-06-12T13:19:24.400303Z"},{"name":"8.14.0","full_size":420607312,"v2":true,"tag_last_pushed":"2024-06-05T11:41:34.315486Z"},{"name":"8.13.4","full_size":392706437,"v2":true,"tag_last_pushed":"2024-05-09T12:10:35.762441Z"},{"name":"7.17.21","full_size":383209870,"v2":true,"tag_last_pushed":"2024-05-02T09:11:24.987043Z"},{"name":"8.13.3","full_size":399800410,"v2":true,"tag_last_pushed":"2024-05-02T08:17:55.745112Z"},{"name":"7.17.20","full_size":376954717,"v2":true,"tag_last_pushed":"2024-04-09T07:47:48.323161Z"},{"name":"8.13.2","full_size":395218302,"v2":true,"tag_last_pushed":"2024-04-08T15:05:10.971886Z"},{"name":"8.13.1","full_size":394584942,"v2":true,"tag_last_pushed":"2024-04-02T07:06:13.833248Z"},{"name":"7.17.19","full_size":373755489,"v2":true,"tag_last_pushed":"2024-03-26T10:06:30.367057Z"},{"name":"8.13.0","full_size":392107905,"v2":true,"tag_last_pushed":"2024-03-26T09:02:24.289713Z"},{"name":"8.12.2","full_size":389498811,"v2":true,"tag_last_pushed":"2024-02-22T12:05:27.543284Z"},{"name":"7.17.18","full_size":374906144,"v2":true,"tag_last_pushed":"2024-02-06T10:19:07.159182Z"},{"name":"8.12.1","full_size":390481050,"v2":true,"tag_last_pushed":"2024-02-06T10:18:10.637615Z"},{"name":"7.17.17","full_size":402023520,"v2":true,"tag_last_pushed":"2024-01-23T15:23:25.61889Z"},{"name":"8.12.0","full_size":423970268,"v2":true,"tag_last_pushed":"2024-01-17T14:41:43.582047Z"},{"name":"8.11.4","full_size":420430034,"v2":true,"tag_last_pushed":"2024-01-11T09:35:04.807825Z"},{"name":"8.11.3","full_size":427798003,"v2":true,"tag_last_pushed":"2023-12-12T11:58:50.828386Z"}],"suffix":[],"fixed_tags":[],"latest_tags":["8.15.2","7.17.24"],"created_time":"2024-09-30 16:01:19"}