{"name":"docker-library-node","repo":"library/node","tags":[{"name":"23.5.0","full_size":406475153,"v2":true,"tag_last_pushed":"2024-12-25T10:48:45.343202Z"},{"name":"22.12.0","full_size":404757415,"v2":true,"tag_last_pushed":"2024-12-25T10:47:16.758304Z"},{"name":"20.18.1","full_size":397539704,"v2":true,"tag_last_pushed":"2024-12-25T10:45:54.324805Z"},{"name":"18.20.5","full_size":395015814,"v2":true,"tag_last_pushed":"2024-12-25T10:44:12.782528Z"}],"suffix":[],"fixed_tags":["lts","lts-alpine"],"latest_tags":["23.5.0","22.12.0","20.18.1","18.20.5"],"created_time":"2024-12-25 16:01:17"}