{"name":"jbp-jetbrains-junie","url":"https://plugins.jetbrains.com/plugin/26104-junie-the-ai-coding-agent-by-jetbrains","display_name":"Jetbrains Plugin: Junie, the AI coding agent by JetBrains","latest":"261.1218.175","versions":["261.1218.175","261.1218.169","261.1218.96","261.1218.79","261.819.54"],"storage_dir":"jetbrains/plugins","download_urls":["https://downloads.marketplace.jetbrains.com/files/26104/1024812/ej-release-261.1218.175.zip#26104-ej-release-261.1218.175.zip"],"created_time":"2026-04-21 04:02:10","jbp_extra":{"xml_id":"org.jetbrains.junie","since":"261.21524","until":"261.*"}}