{"name":"nodepass","url":"https://github.com/yosebyte/nodepass","latest":"1.2.6","versions":["1.2.6","1.2.5","1.2.4","1.2.3","1.2.2","1.2.1","1.2.0","1.1.5","1.1.4","1.1.3","1.1.2","1.1.1","1.1.0","1.0.4","1.0.3","1.0.2","1.0.1","1.0.0"],"download_urls":["https://github.com/yosebyte/nodepass/releases/download/v1.2.6/nodepass_1.2.6_linux_amd64.tar.gz","https://github.com/yosebyte/nodepass/releases/download/v1.2.6/nodepass_1.2.6_windows_amd64.zip","https://github.com/yosebyte/nodepass/archive/refs/tags/v1.2.6.tar.gz"],"created_time":"2025-06-05 04:01:39"}