{"name":"rke2","url":"https://github.com/rancher/rke2","latest":"1.29.2","versions":["1.29.2","1.29.1","1.29.0","1.28.7","1.28.6","1.28.5","1.28.4","1.28.3","1.28.2","1.28.1","1.27.11","1.27.10","1.27.9","1.27.8","1.27.7","1.27.6","1.27.5","1.26.14","1.26.13","1.26.12","1.26.11","1.26.10","1.26.9","1.26.8","1.25.16","1.25.15","1.25.14"],"download_urls":["https://github.com/rancher/rke2/releases/download/v1.29.2+rke2r1/rke2-images.linux-amd64.tar.gz","https://github.com/rancher/rke2/releases/download/v1.29.2+rke2r1/rke2.linux-amd64","https://github.com/rancher/rke2/releases/download/v1.29.2+rke2r1/rke2-windows-amd64.exe"],"created_time":"2024-03-18 04:00:29"}